tock/__init__.py
tock/editor.js
tock/grammars.py
tock/graphs.py
tock/graphviz.py
tock/machines.py
tock/new.py
tock/operations.py
tock/regexps.py
tock/run.py
tock/runs.py
tock/settings.py
tock/syntax.py
tock/tables.py
tock/trees.py
tock-0.25.dist-info/LICENSE.txt
tock-0.25.dist-info/METADATA
tock-0.25.dist-info/WHEEL
tock-0.25.dist-info/top_level.txt
tock-0.25.dist-info/RECORD
