Metadata-Version: 2.1
Name: tock
Version: 0.25
Summary: Theory of Computing Toolkit
Home-page: https://github.org/ND-CSE-30151/tock
Author: David Chiang
Author-email: dchiang@nd.edu
License: MIT
Platform: UNKNOWN
Classifier: Development Status :: 3 - Alpha
Classifier: Intended Audience :: Education
Classifier: Topic :: Education
Classifier: Topic :: Scientific/Engineering :: Mathematics
Classifier: License :: OSI Approved :: MIT License
Classifier: Programming Language :: Python :: 3
Requires-Python: >=3.7
Requires-Dist: openpyxl
